README.md
setup.cfg
setup.py
PythonValidGen/__init__.py
PythonValidGen.egg-info/PKG-INFO
PythonValidGen.egg-info/SOURCES.txt
PythonValidGen.egg-info/dependency_links.txt
PythonValidGen.egg-info/requires.txt
PythonValidGen.egg-info/top_level.txt
PythonValidGen/DataRepresentation/CBOR_JSON_Converter.py
PythonValidGen/DataRepresentation/Document.py
PythonValidGen/DataRepresentation/__init__.py
PythonValidGen/DataRepresentation/Utils/Exceptions.py
PythonValidGen/DataRepresentation/Utils/__init__.py
PythonValidGen/Generator/Generator.py
PythonValidGen/Generator/__init__.py
PythonValidGen/Generator/Templates/template0.txt
PythonValidGen/Generator/Templates/template1.txt
PythonValidGen/JSON_Files/mDL_example_document.json
PythonValidGen/JSON_Files/mDL_example_document1.json
PythonValidGen/JSON_Files/mDL_example_document2.json
PythonValidGen/JSON_Files/mDL_example_document3.json
PythonValidGen/JSON_Files/mDL_specification_prototype.json
PythonValidGen/JSON_Files/mDL_specification_prototype1.json
PythonValidGen/JSON_Files/schema_document.json
PythonValidGen/JSON_Files/schema_document1.json
PythonValidGen/JSON_Files/schema_document2.json
PythonValidGen/JSON_Files/schema_document3.json
PythonValidGen/JSON_Files/standard_format_prototype.json
PythonValidGen/JSON_Files/types_prototype.json
PythonValidGen/Utils/Exceptions.py
PythonValidGen/Utils/__init__.py
PythonValidGen/Validator/Exceptions.py
PythonValidGen/Validator/ValidationFunctions.py
PythonValidGen/Validator/__init__.py
PythonValidGen/Verifier/Verifier.py
PythonValidGen/Verifier/__init__.py