Metadata-Version: 2.1
Name: PythonValidGen
Version: 1.6.0
Summary: Generator capable of verifying the structure of a document and generate a Python program that can process an exemplar
Home-page: https://github.com/LEImDL/PythonValidGen
Author: Ana Almeida, André Figueiredo, Luís Ferreira
License: LICENSE
Platform: UNKNOWN
